{
  "metadata": {
    "api_url": "https://datadistillery.wikibase.cloud/w/api.php",
    "cache_dir": "/home/runner/work/SpiritSafe/SpiritSafe/cache/entities",
    "since": "2026-03-20T11:48:44.598780Z",
    "next_since": "2026-03-20T23:32:43Z",
    "overlap_seconds": 60
  },
  "summary": {
    "changed_count": 36,
    "ignored_count": 0,
    "refreshed_count": 36,
    "deleted_count": 0,
    "missing_count": 0
  },
  "changed_ids": [
    "P192",
    "P193",
    "P195",
    "P196",
    "P197",
    "P198",
    "P199",
    "P200",
    "P201",
    "P206",
    "P207",
    "P208",
    "P209",
    "P214",
    "Q16",
    "Q19",
    "Q21",
    "Q25",
    "Q27",
    "Q28",
    "Q29",
    "Q30",
    "Q32",
    "Q33",
    "Q34",
    "Q35",
    "Q36",
    "Q37",
    "Q38",
    "Q39",
    "Q4",
    "Q40",
    "Q41",
    "Q42",
    "Q43",
    "Q51"
  ],
  "ignored_ids": [],
  "refreshed_ids": [
    "P192",
    "P193",
    "P195",
    "P196",
    "P197",
    "P198",
    "P199",
    "P200",
    "P201",
    "P206",
    "P207",
    "P208",
    "P209",
    "P214",
    "Q16",
    "Q19",
    "Q21",
    "Q25",
    "Q27",
    "Q28",
    "Q29",
    "Q30",
    "Q32",
    "Q33",
    "Q34",
    "Q35",
    "Q36",
    "Q37",
    "Q38",
    "Q39",
    "Q4",
    "Q40",
    "Q41",
    "Q42",
    "Q43",
    "Q51"
  ],
  "deleted_ids": [],
  "missing_ids": []
}